{
  "schemaVersion": 1,
  "id": "melonutilities",
  "version": "${version}",

  "name": "MelonUtilities",
  "description": "An Extensive Utility Mod For BTA Servers.",
  "authors": [
    "MelonModding"
  ],
  "contact": {
    "homepage": "",
    "sources": ""
  },

	"icon": "icon.png",
  "license": "MIT",

  "environment": "*",
  "entrypoints": {
    "main": [
			"MelonUtilities.MelonUtilities"
    ]
	},
  "mixins": [
		"MelonUtilities.mixins.json"
  ],

  "depends": {
		"minecraft": "*",
    "fabricloader": ">=0.15.5"
  },
  "suggests": {
  }
}
